{
  "id": "world-mobile-token",
  "symbol": "wmtx",
  "name": "World Mobile Token",
  "web_slug": "world-mobile-token",
  "asset_platform_id": "ethereum",
  "platforms": {
    "ethereum": "0xdbb5cf12408a3ac17d668037ce289f9ea75439d7",
    "cardano": "e5a42a1a1d3d1da71b0449663c32798725888d2eb0843c4dabeca05a576f726c644d6f62696c65546f6b656e58",
    "arbitrum-one": "0xdbb5cf12408a3ac17d668037ce289f9ea75439d7",
    "base": "0x3e31966d4f81c72d2a55310a6365a56a4393e98d",
    "binance-smart-chain": "0xdbb5cf12408a3ac17d668037ce289f9ea75439d7"
  },
  "detail_platforms": {
    "ethereum": {
      "decimal_place": 6,
      "contract_address": "0xdbb5cf12408a3ac17d668037ce289f9ea75439d7",
      "geckoterminal_url": "https://www.geckoterminal.com/eth/tokens/0xdbb5cf12408a3ac17d668037ce289f9ea75439d7"
    },
    "cardano": {
      "decimal_place": 6,
      "contract_address": "e5a42a1a1d3d1da71b0449663c32798725888d2eb0843c4dabeca05a576f726c644d6f62696c65546f6b656e58"
    },
    "arbitrum-one": {
      "decimal_place": 6,
      "contract_address": "0xdbb5cf12408a3ac17d668037ce289f9ea75439d7",
      "geckoterminal_url": "https://www.geckoterminal.com/arbitrum/tokens/0xdbb5cf12408a3ac17d668037ce289f9ea75439d7"
    },
    "base": {
      "decimal_place": 6,
      "contract_address": "0x3e31966d4f81c72d2a55310a6365a56a4393e98d",
      "geckoterminal_url": "https://www.geckoterminal.com/base/tokens/0x3e31966d4f81c72d2a55310a6365a56a4393e98d"
    },
    "binance-smart-chain": {
      "decimal_place": 6,
      "contract_address": "0xdbb5cf12408a3ac17d668037ce289f9ea75439d7",
      "geckoterminal_url": "https://www.geckoterminal.com/bsc/tokens/0xdbb5cf12408a3ac17d668037ce289f9ea75439d7"
    }
  },
  "block_time_in_minutes": 0,
  "hashing_algorithm": null,
  "categories": [
    "BNB Chain Ecosystem",
    "Arbitrum Ecosystem",
    "Cardano Ecosystem",
    "Ethereum Ecosystem",
    "DePIN",
    "Base Ecosystem",
    "DWF Labs Portfolio"
  ],
  "preview_listing": false,
  "public_notice": "World Mobile Token (WMT) has recently migrated from their <a href=\"https://cardanoscan.io/token/1d7f33bd23d85e1a25d87d86fac4f199c3197a2f7afeb662a0f34e1e776f726c646d6f62696c65746f6b656e\"target=\"_blank\">old contract</a> to new contracts on Cardano, Base, Arbitrum, BSC and Ethereum with a new ticker WMTx. For more information, please visit this <a href=\"https://faq.worldmobiletoken.com/docs/faq-and-support/token-migration/token-migration-guide\">migration guide</a>.<br>",
  "additional_notices": [],
  "description": {
    "en": "World Mobile Token (WMTX) is the utility token that powers the World Mobile network, a decentralized mobile network at the forefront of the DePIN space. World Mobile aims to connect the world by leveraging blockchain technology and a sharing economy. By becoming an AirNode operator or a token staker, anyone can earn rewards for providing telco services to customers or securing the network. The World Mobile network is disrupting the trillion-dollar telco industry and creating a more inclusive, sustainable, and privacy-respecting wireless service for everyone."
  },
  "links": {
    "homepage": [
      "https://worldmobile.io"
    ],
    "whitepaper": "",
    "blockchain_site": [
      "https://bscscan.com/token/0xdbb5cf12408a3ac17d668037ce289f9ea75439d7",
      "https://platform.arkhamintelligence.com/explorer/token/world-mobile-token",
      "https://binplorer.com/address/0xdbb5cf12408a3ac17d668037ce289f9ea75439d7",
      "https://etherscan.io/token/0xDBB5Cf12408a3Ac17d668037Ce289f9eA75439D7",
      "https://ethplorer.io/address/0xDBB5Cf12408a3Ac17d668037Ce289f9eA75439D7",
      "https://arbiscan.io/token/0xDBB5Cf12408a3Ac17d668037Ce289f9eA75439D7",
      "https://basescan.org/token/0x3e31966d4f81C72D2a55310A6365A56A4393E98D"
    ],
    "official_forum_url": [],
    "chat_url": [
      "https://discord.com/invite/Qg54MMMmjG",
      "https://www.instagram.com/WorldMobileTeam/",
      "https://t.me/WorldMobileAnnouncements"
    ],
    "announcement_url": [],
    "snapshot_url": null,
    "twitter_screen_name": "wmchain",
    "facebook_username": "",
    "bitcointalk_thread_identifier": 5343042,
    "telegram_channel_identifier": "WorldMobileTeam",
    "subreddit_url": "https://www.reddit.com/r/WorldMobileToken/",
    "repos_url": {
      "github": [],
      "bitbucket": []
    }
  },
  "image": {
    "thumb": "https://coin-images.coingecko.com/coins/images/17333/thumb/Token_icon_round_1024.png?1741247846",
    "small": "https://coin-images.coingecko.com/coins/images/17333/small/Token_icon_round_1024.png?1741247846",
    "large": "https://coin-images.coingecko.com/coins/images/17333/large/Token_icon_round_1024.png?1741247846"
  },
  "country_origin": "GB",
  "genesis_date": null,
  "contract_address": "0xdbb5cf12408a3ac17d668037ce289f9ea75439d7",
  "sentiment_votes_up_percentage": 50.0,
  "sentiment_votes_down_percentage": 50.0,
  "watchlist_portfolio_users": 17005,
  "market_cap_rank": 432,
  "market_data": {
    "current_price": {
      "aed": 0.496106,
      "ars": 160.55,
      "aud": 0.205962,
      "bch": 0.00027506,
      "bdt": 16.5,
      "bhd": 0.05096,
      "bmd": 0.135089,
      "bnb": 0.00020923,
      "brl": 0.742434,
      "btc": 1.26e-06,
      "cad": 0.184089,
      "chf": 0.107988,
      "clp": 125.88,
      "cny": 0.968261,
      "czk": 2.85,
      "dkk": 0.859888,
      "dot": 0.04099663,
      "eos": 0.27382936,
      "eth": 5.572e-05,
      "eur": 0.115248,
      "gbp": 0.098239,
      "gel": 0.367441,
      "hkd": 1.06,
      "huf": 46.04,
      "idr": 2186.98,
      "ils": 0.458457,
      "inr": 11.57,
      "jpy": 19.48,
      "krw": 182.92,
      "kwd": 0.0412993,
      "lkr": 40.46,
      "ltc": 0.00160393,
      "mmk": 283.42,
      "mxn": 2.55,
      "myr": 0.571763,
      "ngn": 208.49,
      "nok": 1.36,
      "nzd": 0.222526,
      "php": 7.65,
      "pkr": 38.32,
      "pln": 0.488771,
      "rub": 10.64,
      "sar": 0.506642,
      "sek": 1.28,
      "sgd": 0.172059,
      "sol": 0.0009552,
      "thb": 4.39,
      "try": 5.37,
      "twd": 3.95,
      "uah": 5.61,
      "usd": 0.135089,
      "vef": 0.01352643,
      "vnd": 3528.52,
      "xag": 0.00368722,
      "xau": 4.052e-05,
      "xdr": 0.093936,
      "xlm": 0.57490358,
      "xrp": 0.06382625,
      "yfi": 2.693e-05,
      "zar": 2.41,
      "bits": 1.26,
      "link": 0.01034638,
      "sats": 125.9
    },
    "total_value_locked": null,
    "mcap_to_tvl_ratio": null,
    "fdv_to_tvl_ratio": null,
    "roi": null,
    "ath": {
      "aed": 3.6,
      "ars": 618.25,
      "aud": 1.36,
      "bch": 0.00307651,
      "bdt": 84.26,
      "bhd": 0.369278,
      "bmd": 0.979732,
      "bnb": 0.00244923,
      "brl": 5.03,
      "btc": 2.372e-05,
      "cad": 1.24,
      "chf": 0.90352,
      "clp": 781.87,
      "cny": 6.2,
      "czk": 21.02,
      "dkk": 6.42,
      "dot": 0.07302079,
      "eos": 0.62727171,
      "eth": 0.00034361,
      "eur": 0.86223,
      "gbp": 0.721186,
      "gel": 1.71,
      "hkd": 7.64,
      "huf": 306.81,
      "idr": 14027.65,
      "ils": 3.13,
      "inr": 73.52,
      "jpy": 112.99,
      "krw": 1172.39,
      "kwd": 0.296354,
      "lkr": 226.45,
      "ltc": 0.00846909,
      "mmk": 1742.48,
      "mxn": 19.89,
      "myr": 4.1,
      "ngn": 940.43,
      "nok": 8.72,
      "nzd": 1.46,
      "php": 50.27,
      "pkr": 172.77,
      "pln": 3.89,
      "rub": 109.54,
      "sar": 3.68,
      "sek": 9.12,
      "sgd": 0.817983,
      "sol": 0.0011185,
      "thb": 31.55,
      "try": 21.22,
      "twd": 27.31,
      "uah": 27.54,
      "usd": 0.979732,
      "vef": 0.098101,
      "vnd": 22322,
      "xag": 0.0416429,
      "xau": 0.00052247,
      "xdr": 0.698551,
      "xlm": 4.888127,
      "xrp": 1.270227,
      "yfi": 6.504e-05,
      "zar": 14.73,
      "bits": 23.72,
      "link": 0.06558552,
      "sats": 2371.54
    },
    "ath_change_percentage": {
      "aed": -86.21373,
      "ars": -74.03145,
      "aud": -84.88616,
      "bch": -91.05949,
      "bdt": -80.42097,
      "bhd": -86.20004,
      "bmd": -86.21167,
      "bnb": -91.45735,
      "brl": -85.24892,
      "btc": -94.6913,
      "cad": -85.21326,
      "chf": -88.04809,
      "clp": -83.89976,
      "cny": -84.3953,
      "czk": -86.42812,
      "dkk": -86.59673,
      "dot": -43.85622,
      "eos": -56.34597,
      "eth": -83.78377,
      "eur": -86.63376,
      "gbp": -86.37814,
      "gel": -78.4637,
      "hkd": -86.12446,
      "huf": -84.99533,
      "idr": -84.40953,
      "ils": -85.37414,
      "inr": -84.2705,
      "jpy": -82.75802,
      "krw": -84.39769,
      "kwd": -86.06421,
      "lkr": -82.13425,
      "ltc": -81.06139,
      "mmk": -83.73493,
      "mxn": -87.18116,
      "myr": -86.0635,
      "ngn": -77.83068,
      "nok": -84.40223,
      "nzd": -84.80679,
      "php": -84.7814,
      "pkr": -77.81997,
      "pln": -87.44113,
      "rub": -90.28848,
      "sar": -86.2188,
      "sek": -85.95207,
      "sgd": -78.9655,
      "sol": -14.59977,
      "thb": -86.09393,
      "try": -74.68712,
      "twd": -85.54606,
      "uah": -79.62492,
      "usd": -86.21167,
      "vef": -86.21167,
      "vnd": -84.19297,
      "xag": -91.14562,
      "xau": -92.24432,
      "xdr": -86.55272,
      "xlm": -88.23878,
      "xrp": -94.97521,
      "yfi": -58.60081,
      "zar": -83.64747,
      "bits": -94.6913,
      "link": -84.2246,
      "sats": -94.6913
    },
    "ath_date": {
      "aed": "2022-02-17T07:00:01.257Z",
      "ars": "2024-12-13T00:10:59.376Z",
      "aud": "2022-02-17T07:00:01.257Z",
      "bch": "2022-02-22T00:00:44.017Z",
      "bdt": "2022-02-17T07:00:01.257Z",
      "bhd": "2022-02-17T07:00:01.257Z",
      "bmd": "2022-02-17T07:00:01.257Z",
      "bnb": "2022-02-22T00:00:44.017Z",
      "brl": "2022-02-17T07:00:01.257Z",
      "btc": "2022-02-19T08:22:13.736Z",
      "cad": "2022-02-17T07:00:01.257Z",
      "chf": "2022-02-17T07:00:01.257Z",
      "clp": "2022-02-17T07:00:01.257Z",
      "cny": "2022-02-17T07:00:01.257Z",
      "czk": "2022-02-17T07:00:01.257Z",
      "dkk": "2022-02-17T07:00:01.257Z",
      "dot": "2024-09-30T17:24:23.537Z",
      "eos": "2024-09-30T17:24:23.537Z",
      "eth": "2022-02-19T14:03:21.328Z",
      "eur": "2022-02-17T07:00:01.257Z",
      "gbp": "2022-02-17T07:00:01.257Z",
      "gel": "2024-12-13T00:10:59.376Z",
      "hkd": "2022-02-17T07:00:01.257Z",
      "huf": "2022-02-17T09:24:59.298Z",
      "idr": "2022-02-17T07:00:01.257Z",
      "ils": "2022-02-17T08:33:03.312Z",
      "inr": "2022-02-17T07:00:01.257Z",
      "jpy": "2022-02-17T07:00:01.257Z",
      "krw": "2022-02-17T07:00:01.257Z",
      "kwd": "2022-02-17T07:00:01.257Z",
      "lkr": "2022-03-24T14:38:51.117Z",
      "ltc": "2022-02-22T00:00:44.017Z",
      "mmk": "2022-02-17T07:00:01.257Z",
      "mxn": "2022-02-17T07:00:01.257Z",
      "myr": "2022-02-17T07:00:01.257Z",
      "ngn": "2024-12-13T00:10:59.376Z",
      "nok": "2022-02-17T08:33:03.312Z",
      "nzd": "2022-02-17T07:00:01.257Z",
      "php": "2022-02-17T07:00:01.257Z",
      "pkr": "2022-02-17T07:00:01.257Z",
      "pln": "2022-02-17T07:00:01.257Z",
      "rub": "2022-03-07T17:48:46.658Z",
      "sar": "2022-02-17T07:00:01.257Z",
      "sek": "2022-02-17T07:00:01.257Z",
      "sgd": "2024-12-13T00:10:59.376Z",
      "sol": "2025-06-22T02:36:43.747Z",
      "thb": "2022-02-17T07:00:01.257Z",
      "try": "2024-12-13T00:10:59.376Z",
      "twd": "2022-02-17T07:00:01.257Z",
      "uah": "2022-02-17T07:00:01.257Z",
      "usd": "2022-02-17T07:00:01.257Z",
      "vef": "2022-02-17T07:00:01.257Z",
      "vnd": "2022-02-17T07:00:01.257Z",
      "xag": "2022-02-17T07:00:01.257Z",
      "xau": "2022-02-17T07:00:01.257Z",
      "xdr": "2022-02-17T07:00:01.257Z",
      "xlm": "2022-02-24T03:47:47.178Z",
      "xrp": "2022-02-24T03:47:47.178Z",
      "yfi": "2024-11-23T00:54:45.997Z",
      "zar": "2022-02-17T07:00:01.257Z",
      "bits": "2022-02-19T08:22:13.736Z",
      "link": "2022-02-24T07:34:52.873Z",
      "sats": "2022-02-19T08:22:13.736Z"
    },
    "atl": {
      "aed": 0.360079,
      "ars": 20.73,
      "aud": 0.144984,
      "bch": 0.00027267,
      "bdt": 10.61,
      "bhd": 0.03695915,
      "bmd": 0.098034,
      "bnb": 0.00020806,
      "brl": 0.469445,
      "btc": 1.25e-06,
      "cad": 0.129993,
      "chf": 0.088181,
      "clp": 78.32,
      "cny": 0.704177,
      "czk": 2.14,
      "dkk": 0.669927,
      "dot": 0.01187017,
      "eos": 0.10847352,
      "eth": 5.374e-05,
      "eur": 0.089944,
      "gbp": 0.076991,
      "gel": 0.330214,
      "hkd": 0.767218,
      "huf": 33.44,
      "idr": 1472.45,
      "ils": 0.354456,
      "inr": 8.04,
      "jpy": 13.87,
      "krw": 126.31,
      "kwd": 0.03011148,
      "lkr": 30.19,
      "ltc": 0.00097832,
      "mmk": 205.85,
      "mxn": 1.68,
      "myr": 0.454926,
      "ngn": 47.9,
      "nok": 1.051,
      "nzd": 0.159395,
      "php": 5.46,
      "pkr": 28.18,
      "pln": 0.39977,
      "rub": 7.7,
      "sar": 0.367704,
      "sek": 1.058,
      "sgd": 0.131844,
      "sol": 0.00094422,
      "thb": 3.42,
      "try": 2.31,
      "twd": 3.03,
      "uah": 3.62,
      "usd": 0.098034,
      "vef": 0.00981613,
      "vnd": 2306.41,
      "xag": 0.00366565,
      "xau": 4.015e-05,
      "xdr": 0.073102,
      "xlm": 0.5514057,
      "xrp": 0.06314674,
      "yfi": 8.83e-06,
      "zar": 1.79,
      "bits": 1.25,
      "link": 0.00782123,
      "sats": 125.32
    },
    "atl_change_percentage": {
      "aed": 37.77717,
      "ars": 674.57302,
      "aud": 42.05884,
      "bch": 0.87412,
      "bdt": 55.51812,
      "bhd": 37.88242,
      "bmd": 37.79799,
      "bnb": 0.56348,
      "brl": 58.15123,
      "btc": 0.45881,
      "cad": 41.61457,
      "chf": 22.46189,
      "clp": 60.74,
      "cny": 37.50256,
      "czk": 33.39605,
      "dkk": 28.35555,
      "dot": 245.3754,
      "eos": 152.43889,
      "eth": 3.6864,
      "eur": 28.13315,
      "gbp": 27.59734,
      "gel": 11.27352,
      "hkd": 38.21441,
      "huf": 37.66572,
      "idr": 48.52615,
      "ils": 29.34091,
      "inr": 43.79273,
      "jpy": 40.47764,
      "krw": 44.81703,
      "kwd": 37.15466,
      "lkr": 33.99465,
      "ltc": 63.94673,
      "mmk": 37.6785,
      "mxn": 51.85514,
      "myr": 25.68258,
      "ngn": 335.24215,
      "nok": 29.31314,
      "nzd": 39.6062,
      "php": 40.20075,
      "pkr": 35.96468,
      "pln": 22.26294,
      "rub": 38.16516,
      "sar": 37.7855,
      "sek": 21.07962,
      "sgd": 30.50149,
      "sol": 1.16232,
      "thb": 28.4033,
      "try": 132.57839,
      "twd": 30.08455,
      "uah": 54.98776,
      "usd": 37.79799,
      "vef": 37.79799,
      "vnd": 52.98753,
      "xag": 0.58838,
      "xau": 0.93549,
      "xdr": 28.50004,
      "xlm": 4.26145,
      "xrp": 1.07608,
      "yfi": 205.09155,
      "zar": 34.50379,
      "bits": 0.45881,
      "link": 32.28585,
      "sats": 0.45881
    },
    "atl_date": {
      "aed": "2023-06-20T14:46:22.600Z",
      "ars": "2022-11-22T10:05:15.066Z",
      "aud": "2023-06-20T15:15:34.149Z",
      "bch": "2025-06-26T17:20:53.186Z",
      "bdt": "2023-06-20T14:46:22.600Z",
      "bhd": "2023-06-20T14:46:22.600Z",
      "bmd": "2023-06-20T14:46:22.600Z",
      "bnb": "2025-06-26T17:00:54.295Z",
      "brl": "2023-06-20T15:15:34.149Z",
      "btc": "2025-06-26T17:10:40.998Z",
      "cad": "2023-06-20T15:15:34.149Z",
      "chf": "2023-06-20T15:15:34.149Z",
      "clp": "2023-06-20T10:15:34.871Z",
      "cny": "2023-06-20T14:46:22.600Z",
      "czk": "2023-06-20T15:15:34.149Z",
      "dkk": "2023-06-20T15:15:34.149Z",
      "dot": "2022-01-02T23:44:31.261Z",
      "eos": "2022-01-02T23:44:31.261Z",
      "eth": "2024-01-19T17:55:09.887Z",
      "eur": "2023-06-20T15:15:34.149Z",
      "gbp": "2023-06-20T15:15:34.149Z",
      "gel": "2024-01-08T03:35:00.221Z",
      "hkd": "2023-06-20T14:46:22.600Z",
      "huf": "2023-06-20T15:15:34.149Z",
      "idr": "2023-06-20T14:46:22.600Z",
      "ils": "2023-06-20T14:41:18.630Z",
      "inr": "2023-06-20T14:46:22.600Z",
      "jpy": "2023-06-20T15:15:34.149Z",
      "krw": "2023-06-20T15:15:34.149Z",
      "kwd": "2023-06-20T14:46:22.600Z",
      "lkr": "2023-06-20T14:46:22.600Z",
      "ltc": "2023-07-01T08:45:15.700Z",
      "mmk": "2023-06-20T14:46:22.600Z",
      "mxn": "2023-06-20T14:46:22.600Z",
      "myr": "2023-06-20T14:46:22.600Z",
      "ngn": "2023-06-10T10:35:30.854Z",
      "nok": "2023-06-20T10:15:34.871Z",
      "nzd": "2023-06-20T10:15:34.871Z",
      "php": "2023-06-20T14:31:15.969Z",
      "pkr": "2023-06-20T14:46:22.600Z",
      "pln": "2023-06-20T15:15:34.149Z",
      "rub": "2022-11-22T10:05:15.066Z",
      "sar": "2023-06-20T14:46:22.600Z",
      "sek": "2023-06-20T10:15:34.871Z",
      "sgd": "2023-06-20T15:15:34.149Z",
      "sol": "2025-06-26T17:10:40.998Z",
      "thb": "2023-06-20T15:15:34.149Z",
      "try": "2023-06-20T14:46:22.600Z",
      "twd": "2023-06-20T14:46:22.600Z",
      "uah": "2023-06-20T14:46:22.600Z",
      "usd": "2023-06-20T14:46:22.600Z",
      "vef": "2023-06-20T14:46:22.600Z",
      "vnd": "2023-06-20T14:46:22.600Z",
      "xag": "2025-06-26T17:00:54.295Z",
      "xau": "2025-06-23T16:40:20.248Z",
      "xdr": "2023-06-20T14:46:22.600Z",
      "xlm": "2025-05-12T13:25:54.221Z",
      "xrp": "2025-06-25T14:35:44.471Z",
      "yfi": "2023-11-17T08:56:41.950Z",
      "zar": "2023-06-20T09:36:13.765Z",
      "bits": "2025-06-26T17:10:40.998Z",
      "link": "2024-02-12T12:19:51.104Z",
      "sats": "2025-06-26T17:10:40.998Z"
    },
    "market_cap": {
      "aed": 368409294,
      "ars": 119225782376,
      "aud": 152948066,
      "bch": 204285,
      "bdt": 12250403874,
      "bhd": 37843097,
      "bmd": 100317035,
      "bnb": 155378,
      "brl": 551332390,
      "btc": 935.013,
      "cad": 136704431,
      "chf": 80192033,
      "clp": 93481431828,
      "cny": 719032377,
      "czk": 2118424914,
      "dkk": 638554340,
      "dot": 30444792,
      "eos": 203341256,
      "eth": 41379,
      "eur": 85583070,
      "gbp": 72952454,
      "gel": 272862334,
      "hkd": 787458626,
      "huf": 34186146277,
      "idr": 1624052153338,
      "ils": 340450936,
      "inr": 8588251076,
      "jpy": 14466619237,
      "krw": 135836208442,
      "kwd": 30668924,
      "lkr": 30043179551,
      "ltc": 1191184,
      "mmk": 210465138513,
      "mxn": 1893714255,
      "myr": 424591849,
      "ngn": 154822288952,
      "nok": 1009528941,
      "nzd": 165247837,
      "php": 5681305078,
      "pkr": 28457434780,
      "pln": 362962079,
      "rub": 7899799344,
      "sar": 376233320,
      "sek": 951530146,
      "sgd": 127770998,
      "sol": 709395,
      "thb": 3258263877,
      "try": 3989287450,
      "twd": 2931063116,
      "uah": 4166645058,
      "usd": 100317035,
      "vef": 10044745,
      "vnd": 2620280942785,
      "xag": 2738134,
      "xau": 30091,
      "xdr": 69757055,
      "xlm": 427047820,
      "xrp": 47401138,
      "yfi": 19998,
      "zar": 1789026106,
      "bits": 935012822,
      "link": 7683870,
      "sats": 93501282218
    },
    "market_cap_rank": 432,
    "fully_diluted_valuation": {
      "aed": 992216102,
      "ars": 321104117531,
      "aud": 411926453,
      "bch": 550190,
      "bdt": 32993326165,
      "bhd": 101920691,
      "bmd": 270178247,
      "bnb": 418471,
      "brl": 1484872627,
      "btc": 2518,
      "cad": 368178381,
      "chf": 215976708,
      "clp": 251768301070,
      "cny": 1936529602,
      "czk": 5705435091,
      "dkk": 1719782616,
      "dot": 81995252,
      "eos": 547647608,
      "eth": 111443,
      "eur": 230496087,
      "gbp": 196478754,
      "gel": 734884831,
      "hkd": 2120818184,
      "huf": 92071631768,
      "idr": 4373968642759,
      "ils": 916917425,
      "inr": 23130255284,
      "jpy": 38962134794,
      "krw": 365840047105,
      "kwd": 82598894,
      "lkr": 80913611680,
      "ltc": 3208149,
      "mmk": 566833961802,
      "mxn": 5100234468,
      "myr": 1143529430,
      "ngn": 416974193646,
      "nok": 2718907716,
      "nzd": 445052738,
      "php": 15301140551,
      "pkr": 76642814163,
      "pln": 977545424,
      "rub": 21276086819,
      "sar": 1013288114,
      "sek": 2562702812,
      "sgd": 344118468,
      "sol": 1910575,
      "thb": 8775299487,
      "try": 10744124305,
      "twd": 7894068015,
      "uah": 11221791610,
      "usd": 270178247,
      "vef": 27052948,
      "vnd": 7057055806616,
      "xag": 7374464,
      "xau": 81043,
      "xdr": 187872767,
      "xlm": 1150143960,
      "xrp": 127662828,
      "yfi": 53859,
      "zar": 4818283744,
      "bits": 2518217630,
      "link": 20694536,
      "sats": 251821763013
    },
    "market_cap_fdv_ratio": 0.37,
    "total_volume": {
      "aed": 16007501,
      "ars": 5180398232,
      "aud": 6645642,
      "bch": 8875,
      "bdt": 532283952,
      "bhd": 1644295,
      "bmd": 4358807,
      "bnb": 6751,
      "brl": 23955568,
      "btc": 40.622557,
      "cad": 5939851,
      "chf": 3484369,
      "clp": 4061797998,
      "cny": 31242186,
      "czk": 92046237,
      "dkk": 27745390,
      "dot": 1322809,
      "eos": 8835453,
      "eth": 1798,
      "eur": 3718612,
      "gbp": 3169807,
      "gel": 11855955,
      "hkd": 34215328,
      "huf": 1485398948,
      "idr": 70565583524,
      "ils": 14792702,
      "inr": 373162246,
      "jpy": 628579215,
      "krw": 5902126537,
      "kwd": 1332575,
      "lkr": 1305385724,
      "ltc": 51753,
      "mmk": 9144777328,
      "mxn": 82282488,
      "myr": 18448651,
      "ngn": 6727077785,
      "nok": 43864354,
      "nzd": 7180071,
      "php": 246854516,
      "pkr": 1236484608,
      "pln": 15770818,
      "rub": 343248799,
      "sar": 16347458,
      "sek": 41344288,
      "sgd": 5551691,
      "sol": 30821,
      "thb": 141572604,
      "try": 173335811,
      "twd": 127355626,
      "uah": 181042055,
      "usd": 4358807,
      "vef": 436447,
      "vnd": 113852041847,
      "xag": 118973,
      "xau": 1307.47,
      "xdr": 3030966,
      "xlm": 18549996,
      "xrp": 2059435,
      "yfi": 868.835,
      "zar": 77733754,
      "bits": 40622557,
      "link": 333839,
      "sats": 4062255652
    },
    "high_24h": {
      "aed": 0.534155,
      "ars": 173.08,
      "aud": 0.222599,
      "bch": 0.00029647,
      "bdt": 17.81,
      "bhd": 0.054869,
      "bmd": 0.145446,
      "bnb": 0.00022534,
      "brl": 0.808676,
      "btc": 1.36e-06,
      "cad": 0.199037,
      "chf": 0.116623,
      "clp": 137.21,
      "cny": 1.043,
      "czk": 3.08,
      "dkk": 0.927234,
      "dot": 0.04365223,
      "eos": 0.29026533,
      "eth": 5.943e-05,
      "eur": 0.124285,
      "gbp": 0.106085,
      "gel": 0.395614,
      "hkd": 1.14,
      "huf": 49.72,
      "idr": 2361.87,
      "ils": 0.493728,
      "inr": 12.47,
      "jpy": 21.0,
      "krw": 197.2,
      "kwd": 0.04448384,
      "lkr": 43.67,
      "ltc": 0.00170742,
      "mmk": 305.15,
      "mxn": 2.75,
      "myr": 0.615092,
      "ngn": 225.15,
      "nok": 1.47,
      "nzd": 0.240265,
      "php": 8.25,
      "pkr": 41.29,
      "pln": 0.527859,
      "rub": 11.4,
      "sar": 0.545525,
      "sek": 1.38,
      "sgd": 0.18551,
      "sol": 0.00101392,
      "thb": 4.73,
      "try": 5.78,
      "twd": 4.26,
      "uah": 6.06,
      "usd": 0.145446,
      "vef": 0.01456353,
      "vnd": 3799.04,
      "xag": 0.00397805,
      "xau": 4.355e-05,
      "xdr": 0.10157,
      "xlm": 0.60838676,
      "xrp": 0.06693907,
      "yfi": 2.862e-05,
      "zar": 2.58,
      "bits": 1.36,
      "link": 0.01103284,
      "sats": 135.63
    },
    "low_24h": {
      "aed": 0.493723,
      "ars": 159.75,
      "aud": 0.20507,
      "bch": 0.00027267,
      "bdt": 16.42,
      "bhd": 0.050712,
      "bmd": 0.13444,
      "bnb": 0.00020806,
      "brl": 0.739285,
      "btc": 1.25e-06,
      "cad": 0.183211,
      "chf": 0.107374,
      "clp": 125.47,
      "cny": 0.963649,
      "czk": 2.84,
      "dkk": 0.855212,
      "dot": 0.04066109,
      "eos": 0.27259501,
      "eth": 5.531e-05,
      "eur": 0.114618,
      "gbp": 0.097743,
      "gel": 0.365676,
      "hkd": 1.055,
      "huf": 45.8,
      "idr": 2175.11,
      "ils": 0.456254,
      "inr": 11.51,
      "jpy": 19.39,
      "krw": 181.94,
      "kwd": 0.04109791,
      "lkr": 40.26,
      "ltc": 0.00159257,
      "mmk": 282.05,
      "mxn": 2.54,
      "myr": 0.568545,
      "ngn": 207.55,
      "nok": 1.35,
      "nzd": 0.221527,
      "php": 7.61,
      "pkr": 38.07,
      "pln": 0.48614,
      "rub": 10.59,
      "sar": 0.50425,
      "sek": 1.27,
      "sgd": 0.171176,
      "sol": 0.00094422,
      "thb": 4.37,
      "try": 5.35,
      "twd": 3.93,
      "uah": 5.58,
      "usd": 0.13444,
      "vef": 0.01346143,
      "vnd": 3511.55,
      "xag": 0.00366565,
      "xau": 4.036e-05,
      "xdr": 0.093485,
      "xlm": 0.5717868,
      "xrp": 0.0633188,
      "yfi": 2.658e-05,
      "zar": 2.39,
      "bits": 1.25,
      "link": 0.01027984,
      "sats": 125.32
    },
    "price_change_24h": -0.0077356693980948,
    "price_change_percentage_24h": -5.41621,
    "price_change_percentage_7d": -6.25691,
    "price_change_percentage_14d": -18.91015,
    "price_change_percentage_30d": -21.06613,
    "price_change_percentage_60d": -25.9368,
    "price_change_percentage_200d": -74.9767,
    "price_change_percentage_1y": -45.32115,
    "market_cap_change_24h": -5454188.7547802,
    "market_cap_change_percentage_24h": -5.15659,
    "price_change_24h_in_currency": {
      "aed": -0.028408859081033133,
      "ars": -9.408715544113448,
      "aud": -0.013513912723022131,
      "bch": -2.100686324229e-05,
      "bdt": -0.9644213150347127,
      "bhd": -0.002919879137175577,
      "bmd": -0.007735669398094863,
      "bnb": -1.2058185191088e-05,
      "brl": -0.04956998662777479,
      "btc": -6.9546638552e-08,
      "cad": -0.011982108390387242,
      "chf": -0.006897193273093197,
      "clp": -7.895545842579708,
      "cny": -0.05602462245532014,
      "czk": -0.17845312434681615,
      "dkk": -0.05437002188024376,
      "dot": -0.001160288233711095,
      "eos": -0.009609264742517554,
      "eth": -3.334806160749e-06,
      "eur": -0.007290913201968924,
      "gbp": -0.00634993069192985,
      "gel": -0.021041020762817775,
      "hkd": -0.0607591042746618,
      "huf": -3.062950879219933,
      "idr": -139.9139880312914,
      "ils": -0.027969676291385137,
      "inr": -0.7134040788796927,
      "jpy": -1.263755349020812,
      "krw": -11.100116040594088,
      "kwd": -0.002357807632613479,
      "lkr": -2.3838760206148564,
      "ltc": -8.5205635849983e-05,
      "mmk": -16.22943439720285,
      "mxn": -0.1494647234555022,
      "myr": -0.033169693673759104,
      "ngn": -13.069859230454398,
      "nok": -0.08841430483659463,
      "nzd": -0.01413716444599386,
      "php": -0.45130987653956467,
      "pkr": -2.346033596574287,
      "pln": -0.0319264786094251,
      "rub": -0.5701296223760028,
      "sar": -0.029030897129721622,
      "sek": -0.07419155852921278,
      "sgd": -0.010517409877672579,
      "sol": -3.9750712852857e-05,
      "thb": -0.2633681812240152,
      "try": -0.3034950522795947,
      "twd": -0.25265752330327995,
      "uah": -0.33149405661775333,
      "usd": -0.007735669398094863,
      "vef": -0.000774572576831226,
      "vnd": -207.05453571867065,
      "xag": -0.000254703614410163,
      "xau": -2.373236389366e-06,
      "xdr": -0.006518859523894777,
      "xlm": -0.013930298930696416,
      "xrp": -0.001420378297987537,
      "yfi": -9.53214408328e-07,
      "zar": -0.1263247365772755,
      "bits": -0.06954663855154553,
      "link": -0.000536968983280582,
      "sats": -6.95466385515455
    },
    "price_change_percentage_1h_in_currency": {
      "aed": -0.35764,
      "ars": -0.41794,
      "aud": -0.30167,
      "bch": 0.01799,
      "bdt": -0.35764,
      "bhd": -0.35791,
      "bmd": -0.35764,
      "bnb": -0.15022,
      "brl": -0.39027,
      "btc": -0.3347,
      "cad": -0.29318,
      "chf": -0.31412,
      "clp": -0.62425,
      "cny": -0.48468,
      "czk": -0.30581,
      "dkk": -0.3069,
      "dot": -0.19935,
      "eos": -0.32785,
      "eth": -0.18455,
      "eur": -0.30319,
      "gbp": -0.3039,
      "gel": -0.35764,
      "hkd": -0.35955,
      "huf": -0.33876,
      "idr": -0.30594,
      "ils": -0.35764,
      "inr": -0.34706,
      "jpy": -0.33352,
      "krw": -0.33621,
      "kwd": -0.35569,
      "lkr": -0.35764,
      "ltc": 0.01097,
      "mmk": -0.35764,
      "mxn": -0.45878,
      "myr": -0.35764,
      "ngn": -0.35764,
      "nok": -0.30754,
      "nzd": -0.32672,
      "php": -0.35764,
      "pkr": -0.35764,
      "pln": -0.30016,
      "rub": -0.35334,
      "sar": -0.35708,
      "sek": -0.33038,
      "sgd": -0.3164,
      "sol": 0.23645,
      "thb": -0.329,
      "try": -0.35538,
      "twd": -0.14027,
      "uah": -0.35764,
      "usd": -0.35764,
      "vef": -0.35764,
      "vnd": -0.35764,
      "xag": -0.26655,
      "xau": -0.32109,
      "xdr": -0.35764,
      "xlm": -0.29601,
      "xrp": -0.26646,
      "yfi": 0.09001,
      "zar": -0.12462,
      "bits": -0.3347,
      "link": -0.12994,
      "sats": -0.3347
    },
    "price_change_percentage_24h_in_currency": {
      "aed": -5.41621,
      "ars": -5.53583,
      "aud": -6.15734,
      "bch": -7.09541,
      "bdt": -5.52328,
      "bhd": -5.41922,
      "bmd": -5.41621,
      "bnb": -5.44911,
      "brl": -6.25881,
      "btc": -5.23487,
      "cad": -6.11112,
      "chf": -6.00355,
      "clp": -5.90192,
      "cny": -5.46963,
      "czk": -5.88729,
      "dkk": -5.9469,
      "dot": -2.75231,
      "eos": -3.39025,
      "eth": -5.64697,
      "eur": -5.94989,
      "gbp": -6.07132,
      "gel": -5.41621,
      "hkd": -5.41929,
      "huf": -6.23837,
      "idr": -6.01292,
      "ils": -5.75003,
      "inr": -5.81019,
      "jpy": -6.09193,
      "krw": -5.72113,
      "kwd": -5.40074,
      "lkr": -5.56453,
      "ltc": -5.04434,
      "mmk": -5.41621,
      "mxn": -5.53661,
      "myr": -5.48321,
      "ngn": -5.89912,
      "nok": -6.10654,
      "nzd": -5.97355,
      "php": -5.57045,
      "pkr": -5.76884,
      "pln": -6.13148,
      "rub": -5.08675,
      "sar": -5.41952,
      "sek": -5.47322,
      "sgd": -5.76056,
      "sol": -3.99525,
      "thb": -5.66261,
      "try": -5.34742,
      "twd": -6.01612,
      "uah": -5.57848,
      "usd": -5.41621,
      "vef": -5.41621,
      "vnd": -5.54278,
      "xag": -6.46141,
      "xau": -5.53274,
      "xdr": -6.48934,
      "xlm": -2.36574,
      "xrp": -2.17694,
      "yfi": -3.41896,
      "zar": -4.98232,
      "bits": -5.23487,
      "link": -4.93386,
      "sats": -5.23487
    },
    "price_change_percentage_7d_in_currency": {
      "aed": -6.25691,
      "ars": -4.32446,
      "aud": -7.50003,
      "bch": -5.75746,
      "bdt": -6.31468,
      "bhd": -6.23976,
      "bmd": -6.25691,
      "bnb": -6.73284,
      "brl": -6.18692,
      "btc": -8.67748,
      "cad": -6.87597,
      "chf": -8.39086,
      "clp": -7.41244,
      "cny": -6.52816,
      "czk": -8.35605,
      "dkk": -8.17559,
      "dot": 1.17272,
      "eos": -3.46704,
      "eth": -2.85878,
      "eur": -8.19707,
      "gbp": -8.28241,
      "gel": -6.25691,
      "hkd": -6.25888,
      "huf": -9.09215,
      "idr": -7.29867,
      "ils": -8.88687,
      "inr": -7.45282,
      "jpy": -7.09251,
      "krw": -7.83964,
      "kwd": -6.4616,
      "lkr": -6.53271,
      "ltc": -5.42493,
      "mmk": -6.25691,
      "mxn": -7.18847,
      "myr": -6.86206,
      "ngn": -6.57653,
      "nok": -6.12998,
      "nzd": -7.60415,
      "php": -7.43937,
      "pkr": -6.14607,
      "pln": -8.90392,
      "rub": -5.812,
      "sar": -6.31049,
      "sek": -7.91599,
      "sgd": -7.26985,
      "sol": -3.96523,
      "thb": -7.14978,
      "try": -5.7752,
      "twd": -7.4542,
      "uah": -6.67141,
      "usd": -6.25691,
      "vef": -6.25691,
      "vnd": -6.281,
      "xag": -6.88662,
      "xau": -5.27798,
      "xdr": -8.10196,
      "xlm": -0.36755,
      "xrp": -3.85984,
      "yfi": -6.63447,
      "zar": -7.45219,
      "bits": -8.67748,
      "link": -5.9727,
      "sats": -8.67748
    },
    "price_change_percentage_14d_in_currency": {
      "aed": -18.91015,
      "ars": -18.63743,
      "aud": -19.29324,
      "bch": -27.16678,
      "bdt": -18.95022,
      "bhd": -18.87424,
      "bmd": -18.91015,
      "bnb": -16.2587,
      "brl": -19.61806,
      "btc": -18.14625,
      "cad": -18.75646,
      "chf": -20.1485,
      "clp": -18.77417,
      "cny": -18.97459,
      "czk": -19.98774,
      "dkk": -19.8977,
      "dot": 0.44837,
      "eos": -3.73403,
      "eth": -7.56388,
      "eur": -19.92423,
      "gbp": -19.85551,
      "gel": -19.35489,
      "hkd": -18.908,
      "huf": -20.32906,
      "idr": -19.05987,
      "ils": -22.61092,
      "inr": -18.89727,
      "jpy": -18.53776,
      "krw": -19.05011,
      "kwd": -18.93667,
      "lkr": -18.79046,
      "ltc": -13.66341,
      "mmk": -18.91015,
      "mxn": -19.07959,
      "myr": -18.74697,
      "ngn": -18.74536,
      "nok": -17.92764,
      "nzd": -19.03853,
      "php": -17.55409,
      "pkr": -18.52962,
      "pln": -20.47265,
      "rub": -20.17887,
      "sar": -18.93084,
      "sek": -18.58239,
      "sgd": -19.24517,
      "sol": -8.23333,
      "thb": -18.61531,
      "try": -18.0565,
      "twd": -19.86731,
      "uah": -18.75033,
      "usd": -18.91015,
      "vef": -18.91015,
      "vnd": -18.64931,
      "xag": -19.80324,
      "xau": -17.72245,
      "xdr": -20.37618,
      "xlm": -5.01692,
      "xrp": -13.69629,
      "yfi": -11.28112,
      "zar": -18.65727,
      "bits": -18.14625,
      "link": -9.79653,
      "sats": -18.14625
    },
    "price_change_percentage_30d_in_currency": {
      "aed": -21.07752,
      "ars": -18.8806,
      "aud": -22.44954,
      "bch": -32.31327,
      "bdt": -21.04779,
      "bhd": -21.01881,
      "bmd": -21.06613,
      "bnb": -15.34,
      "brl": -23.25684,
      "btc": -18.853,
      "cad": -21.94541,
      "chf": -23.73857,
      "clp": -21.668,
      "cny": -21.37328,
      "czk": -24.11589,
      "dkk": -23.63243,
      "dot": 10.17259,
      "eos": 23.33469,
      "eth": -12.26109,
      "eur": -23.68237,
      "gbp": -22.45313,
      "gel": -21.55638,
      "hkd": -20.95219,
      "huf": -24.47707,
      "idr": -21.51304,
      "ils": -24.20534,
      "inr": -20.80808,
      "jpy": -21.12766,
      "krw": -22.2967,
      "kwd": -21.29525,
      "lkr": -21.14408,
      "ltc": -9.55788,
      "mmk": -21.06613,
      "mxn": -22.64963,
      "myr": -21.18717,
      "ngn": -23.10833,
      "nok": -21.80303,
      "nzd": -22.65703,
      "php": -19.52073,
      "pkr": -20.48674,
      "pln": -23.75385,
      "rub": -22.54108,
      "sar": -21.07434,
      "sek": -22.15058,
      "sgd": -21.99569,
      "sol": -0.24945,
      "thb": -21.84536,
      "try": -19.58778,
      "twd": -23.18129,
      "uah": -21.35982,
      "usd": -21.06613,
      "vef": -21.06613,
      "vnd": -20.4494,
      "xag": -28.46034,
      "xau": -21.82453,
      "xdr": -23.29889,
      "xlm": -2.45908,
      "xrp": -12.52009,
      "yfi": -10.24635,
      "zar": -21.54367,
      "bits": -18.853,
      "link": -2.9707,
      "sats": -18.853
    },
    "price_change_percentage_60d_in_currency": {
      "aed": -25.94789,
      "ars": -24.34481,
      "aud": -27.62915,
      "bch": -47.11997,
      "bdt": -25.55783,
      "bhd": -25.86762,
      "bmd": -25.9368,
      "bnb": -30.99208,
      "brl": -28.42806,
      "btc": -35.06439,
      "cad": -27.33002,
      "chf": -28.50491,
      "clp": -26.18157,
      "cny": -27.15735,
      "czk": -28.83887,
      "dkk": -28.23383,
      "dot": -8.27417,
      "eos": 0.07651,
      "eth": -45.03477,
      "eur": -27.90883,
      "gbp": -28.29639,
      "gel": -26.41026,
      "hkd": -25.0744,
      "huf": -29.28771,
      "idr": -28.75839,
      "ils": -30.64296,
      "inr": -25.74072,
      "jpy": -25.6615,
      "krw": -30.27713,
      "kwd": -26.09827,
      "lkr": -25.97302,
      "ltc": -24.05522,
      "mmk": -25.9368,
      "mxn": -28.31587,
      "myr": -28.33276,
      "ngn": -28.86811,
      "nok": -28.58805,
      "nzd": -27.21417,
      "php": -25.35222,
      "pkr": -25.21844,
      "pln": -28.7355,
      "rub": -29.09235,
      "sar": -25.94657,
      "sek": -27.45774,
      "sgd": -28.2132,
      "sol": -21.88443,
      "thb": -28.12823,
      "try": -23.34413,
      "twd": -33.48563,
      "uah": -26.44001,
      "usd": -25.9368,
      "vef": -25.9368,
      "vnd": -25.65598,
      "xag": -33.06144,
      "xau": -26.27597,
      "xdr": -28.36702,
      "xlm": -9.49226,
      "xrp": -21.851,
      "yfi": -9.2694,
      "zar": -29.32431,
      "bits": -35.06439,
      "link": -17.4289,
      "sats": -35.06439
    },
    "price_change_percentage_200d_in_currency": {
      "aed": -74.98045,
      "ars": -70.65248,
      "aud": -75.61344,
      "bch": -68.28418,
      "bdt": -74.45758,
      "bhd": -74.94249,
      "bmd": -74.9767,
      "bnb": -71.33288,
      "brl": -77.41707,
      "btc": -76.66981,
      "cad": -75.92074,
      "chf": -77.36082,
      "clp": -76.10186,
      "cny": -75.33018,
      "czk": -77.74736,
      "dkk": -77.43428,
      "dot": -21.34755,
      "eos": -33.48957,
      "eth": -58.81278,
      "eur": -77.43407,
      "gbp": -76.81376,
      "gel": -75.77816,
      "hkd": -74.75171,
      "huf": -78.22376,
      "idr": -74.46576,
      "ils": -76.37198,
      "inr": -74.69899,
      "jpy": -75.94036,
      "krw": -76.22643,
      "kwd": -75.08582,
      "lkr": -74.21572,
      "ltc": -60.21037,
      "mmk": -74.9767,
      "mxn": -76.6069,
      "myr": -76.0355,
      "ngn": -75.96983,
      "nok": -77.42788,
      "nzd": -75.96475,
      "php": -75.5249,
      "pkr": -74.49881,
      "pln": -77.56911,
      "rub": -80.05792,
      "sar": -75.02069,
      "sek": -78.29629,
      "sgd": -76.24899,
      "sol": -58.22827,
      "thb": -76.13632,
      "try": -71.35589,
      "twd": -77.44085,
      "uah": -74.92984,
      "usd": -74.9767,
      "vef": -74.9767,
      "vnd": -74.25437,
      "xag": -78.84936,
      "xau": -80.23648,
      "xdr": -77.14921,
      "xlm": -47.82612,
      "xrp": -69.27036,
      "yfi": -32.93134,
      "zar": -75.29505,
      "bits": -76.66981,
      "link": -50.32064,
      "sats": -76.66981
    },
    "price_change_percentage_1y_in_currency": {
      "aed": -45.32934,
      "ars": -28.66569,
      "aud": -44.5027,
      "bch": -58.03633,
      "bdt": -43.18761,
      "bhd": -45.27357,
      "bmd": -45.32115,
      "bnb": -51.68272,
      "brl": -45.48977,
      "btc": -68.86894,
      "cad": -45.58339,
      "chf": -51.26744,
      "clp": -46.1885,
      "cny": -46.05571,
      "czk": -50.46675,
      "dkk": -50.136,
      "dot": -3.5793,
      "eos": -36.98261,
      "eth": -24.20711,
      "eur": -50.15489,
      "gbp": -49.77194,
      "gel": -47.07243,
      "hkd": -45.03719,
      "huf": -49.80297,
      "idr": -46.11452,
      "ils": -50.54598,
      "inr": -43.98153,
      "jpy": -50.91481,
      "krw": -46.8294,
      "kwd": -45.50564,
      "lkr": -46.42361,
      "ltc": -53.8338,
      "mmk": -53.77906,
      "mxn": -43.50674,
      "myr": -50.89057,
      "ngn": -44.33175,
      "nok": -48.44568,
      "nzd": -45.19913,
      "php": -47.46892,
      "pkr": -44.31513,
      "pln": -51.01376,
      "rub": -50.64745,
      "sar": -45.33813,
      "sek": -50.90689,
      "sgd": -48.73547,
      "sol": -47.47564,
      "thb": -51.89733,
      "try": -33.83034,
      "twd": -50.91356,
      "uah": -43.96282,
      "usd": -45.32115,
      "vef": -45.32115,
      "vnd": -43.92128,
      "xag": -56.83167,
      "xau": -62.24079,
      "xdr": -50.06342,
      "xlm": -78.97552,
      "xrp": -87.91749,
      "yfi": -37.29596,
      "zar": -46.19854,
      "bits": -68.86894,
      "link": -41.46736,
      "sats": -68.86894
    },
    "market_cap_change_24h_in_currency": {
      "aed": -20030235.492492795,
      "ars": -6641433938.84317,
      "aud": -9589303.822378606,
      "bch": -14898.648620176682,
      "bdt": -680686225.98493,
      "bhd": -2058780.1495893523,
      "bmd": -5454188.754780188,
      "bnb": -8539.352884549211,
      "brl": -35200774.40929437,
      "btc": -50.34887337360999,
      "cad": -8499362.475052118,
      "chf": -4888329.392401025,
      "clp": -5591299917.187897,
      "cny": -39521816.77319968,
      "czk": -126357864.26723266,
      "dkk": -38516770.55137515,
      "dot": -805934.6029381081,
      "eos": -6548832.756465554,
      "eth": -2377.9097334204707,
      "eur": -5165148.7276919335,
      "gbp": -4502861.336730182,
      "gel": -14835393.413002312,
      "hkd": -42840717.13034487,
      "huf": -2174745084.1948814,
      "idr": -99170272430.1875,
      "ils": -19781523.19081515,
      "inr": -504815423.9356594,
      "jpy": -896297023.2329941,
      "krw": -7848563168.868378,
      "kwd": -1662166.0249455422,
      "lkr": -1683184360.1310387,
      "ltc": -60333.14103055326,
      "mmk": -11442888007.528992,
      "mxn": -105505079.9714725,
      "myr": -23402167.57456082,
      "ngn": -9255321219.591705,
      "nok": -62713402.572858214,
      "nzd": -10017195.375918955,
      "php": -318674076.4482002,
      "pkr": -1659500235.2360573,
      "pln": -22650185.669978917,
      "rub": -400595396.5529051,
      "sar": -20469480.06629902,
      "sek": -52339246.19988167,
      "sgd": -7439106.772999421,
      "sol": -27649.368130364106,
      "thb": -186123124.6981244,
      "try": -213838739.24849033,
      "twd": -179086820.18593216,
      "uah": -234088430.84099388,
      "usd": -5454188.754780188,
      "vef": -546127.9200161453,
      "vnd": -146165403090.98242,
      "xag": -181130.21116554877,
      "xau": -1675.1738115114713,
      "xdr": -4636711.779732227,
      "xlm": -9434199.354308724,
      "xrp": -934491.7091919854,
      "yfi": -657.3554864553153,
      "zar": -88654900.64617229,
      "bits": -50348873.37361002,
      "link": -385603.1957756113,
      "sats": -5034887337.360992
    },
    "market_cap_change_percentage_24h_in_currency": {
      "aed": -5.15659,
      "ars": -5.27654,
      "aud": -5.89975,
      "bch": -6.79733,
      "bdt": -5.26395,
      "bhd": -5.15961,
      "bmd": -5.15659,
      "bnb": -5.20954,
      "brl": -6.0015,
      "btc": -5.10968,
      "cad": -5.8534,
      "chf": -5.74554,
      "clp": -5.64363,
      "cny": -5.21015,
      "czk": -5.62896,
      "dkk": -5.68873,
      "dot": -2.57893,
      "eos": -3.12012,
      "eth": -5.43438,
      "eur": -5.69174,
      "gbp": -5.8135,
      "gel": -5.15659,
      "hkd": -5.15967,
      "huf": -5.981,
      "idr": -5.75493,
      "ils": -5.49132,
      "inr": -5.55165,
      "jpy": -5.83416,
      "krw": -5.46235,
      "kwd": -5.14108,
      "lkr": -5.30532,
      "ltc": -4.8208,
      "mmk": -5.15659,
      "mxn": -5.27731,
      "myr": -5.22377,
      "ngn": -5.64082,
      "nok": -5.84881,
      "nzd": -5.71546,
      "php": -5.31125,
      "pkr": -5.51019,
      "pln": -5.87382,
      "rub": -4.82622,
      "sar": -5.1599,
      "sek": -5.21375,
      "sgd": -5.50189,
      "sol": -3.75138,
      "thb": -5.40366,
      "try": -5.08761,
      "twd": -5.75814,
      "uah": -5.3193,
      "usd": -5.15659,
      "vef": -5.15659,
      "vnd": -5.28351,
      "xag": -6.20465,
      "xau": -5.27344,
      "xdr": -6.23266,
      "xlm": -2.16142,
      "xrp": -1.93334,
      "yfi": -3.18252,
      "zar": -4.72151,
      "bits": -5.10968,
      "link": -4.77854,
      "sats": -5.10968
    },
    "total_supply": 2000000000.0,
    "max_supply": 2000000000.0,
    "max_supply_infinite": false,
    "circulating_supply": 742598900.898187,
    "last_updated": "2025-06-26T18:43:08.151Z"
  },
  "community_data": {
    "facebook_likes": null,
    "reddit_average_posts_48h": 0.0,
    "reddit_average_comments_48h": 0.0,
    "reddit_subscribers": 0,
    "reddit_accounts_active_48h": 0,
    "telegram_channel_user_count": 9083,
    "twitter_followers": 0,
    "discord_members": 0
  },
  "developer_data": {
    "forks": 0,
    "stars": 0,
    "subscribers": 0,
    "total_issues": 0,
    "closed_issues": 0,
    "pull_requests_merged": 0,
    "pull_request_contributors": 0,
    "code_additions_deletions_4_weeks": {
      "additions": null,
      "deletions": null
    },
    "commit_count_4_weeks": 0,
    "last_4_weeks_commit_activity_series": []
  },
  "status_updates": [],
  "last_updated": "2025-06-26T18:43:08.151Z"
}